django_mozilla_rna-2.1.2.dist-info/DESCRIPTION.rst
django_mozilla_rna-2.1.2.dist-info/METADATA
django_mozilla_rna-2.1.2.dist-info/RECORD
django_mozilla_rna-2.1.2.dist-info/WHEEL
django_mozilla_rna-2.1.2.dist-info/metadata.json
django_mozilla_rna-2.1.2.dist-info/top_level.txt
rna/__init__.py
rna/admin.py
rna/fields.py
rna/filters.py
rna/middleware.py
rna/models.py
rna/serializers.py
rna/urls.py
rna/utils.py
rna/views.py
rna/management/__init__.py
rna/management/commands/__init__.py
rna/management/commands/export_json.py
rna/management/commands/rnasync.py
rna/static/js/jquery-2.1.1.js
rna/static/js/jquery-2.1.1.min.js
rna/static/js/react.js
rna/static/js/react.min.js
rna/static/js/releasenotes.js
rna/static/js/mori/mori.js
rna/static/jsx/releasenotes.js
rna/templates/admin/rna/note/change_form.html
rna/templates/admin/rna/release/change_form.html
