Metadata-Version: 2.0
Name: django-mozilla-rna
Version: 2.1.2
Summary: Django app for managing Mozilla product release notes.
Home-page: https://github.com/mozilla/rna/
Author: Josh Mize
Author-email: jmize@mozilla.com
License: MPL 2.0
Platform: UNKNOWN
Classifier: Development Status :: 4 - Beta
Classifier: Environment :: Web Environment
Classifier: Framework :: Django
Classifier: Intended Audience :: Developers
Classifier: Programming Language :: Python
Classifier: Programming Language :: Python :: 2.7
Requires-Dist: Django (>=1.8,<1.9)
Requires-Dist: django-extensions (>=1.2.0)
Requires-Dist: django-synctool
Requires-Dist: djangorestframework (>=3.3.0)
